README.md
setup.cfg
setup.py
rada_student_package/__init__.py
rada_student_package/descriptors.py
rada_student_package/rada_consoles.py
rada_student_package/rada_databases.py
rada_student_package/rada_factories.py
rada_student_package/rada_metaclass.py
rada_student_package/rada_models.py
rada_student_package/utils.py
rada_student_package/verh_rada.py
rada_student_package.egg-info/PKG-INFO
rada_student_package.egg-info/SOURCES.txt
rada_student_package.egg-info/dependency_links.txt
rada_student_package.egg-info/entry_points.txt
rada_student_package.egg-info/not-zip-safe
rada_student_package.egg-info/top_level.txt