Metadata-Version: 1.0
Name: rada-student-package
Version: 0.2.dev0
Summary: No description
Home-page: UNKNOWN
Author: Students
Author-email: UNKNOWN
License: UNKNOWN
Platform: UNKNOWN
